tootbot/__init__.py
tootbot/app.py
tootbot/collect.py
tootbot/control.py
tootbot/create_config.py
tootbot/debug.py
tootbot/monitoring.py
tootbot/publish.py
tootbot-8.2.0.dist-info/entry_points.txt
tootbot-8.2.0.dist-info/WHEEL
tootbot-8.2.0.dist-info/METADATA
tootbot-8.2.0.dist-info/RECORD
