Metadata-Version: 2.1
Name: tootbot
Version: 8.2.0
Summary: A Python bot that looks up posts from specified subreddits and/or redditors and automatically posts them on Mastodon
Author-email: marvin8 <marvin8@tuta.io>
Requires-Python: >=3.8, <3.12
Classifier: Programming Language :: Python :: 3
Classifier: Operating System :: OS Independent
Classifier: Environment :: Console
Classifier: Intended Audience :: Developers
Classifier: Intended Audience :: End Users/Desktop
Requires-Dist: aiohttp>=3.9.1
Requires-Dist: aiosqlite>=0.17.0
Requires-Dist: arrow>=1.3.0
Requires-Dist: asyncpraw>=7.7.1
Requires-Dist: certifi>=2023.11.17
Requires-Dist: imgurpython>=1.1.7
Requires-Dist: minimal-activitypub>=0.5.11
Requires-Dist: outdated>=0.2.2
Requires-Dist: python-magic>=0.4.27
Requires-Dist: tqdm>=4.66.1
Requires-Dist: urllib3>=2.1.0
Requires-Dist: yt-dlp>=2023.11.16
Project-URL: Bug Tracker, https://codeberg.org/MarvinsMastodonTools/tootbot/issues
Project-URL: Changelog, https://codeberg.org/MarvinsMastodonTools/tootbot/src/branch/main/CHANGELOG.rst
Project-URL: Documentation, https://marvinsmastodontools.codeberg.page/tootbot/
Project-URL: homepage, https://codeberg.org/MarvinsMastodonTools/tootbot
Project-URL: repository, https://codeberg.org/MarvinsMastodonTools/tootbot
